WinevtJSON/__init__.py
WinevtJSON/main.py
winevt-json/__init__.py
winevt-json/main.py
winevt_json/__init__.py
winevt_json/main.py
winevt_json-0.1.2.dist-info/METADATA
winevt_json-0.1.2.dist-info/RECORD
winevt_json-0.1.2.dist-info/WHEEL
winevt_json-0.1.2.dist-info/entry_points.txt
winevt_json-0.1.2.dist-info/top_level.txt
